{
  "questions": [
    {
      "text": "Экологический кодекс РК был издан",
      "answer": "9.07.2007"
    },
    {
      "text": "Термин 'экологическая ниша' был предложен в 1917г",
      "answer": "Гриннелом"
    },
    {
      "text": "Вода - это ...",
      "answer": "жизнь"
    },
    {
      "text": "Факторы, возникающие в результате деятельности человека, называются",
      "answer": "Антропогенные"
    },
    {
      "text": "МЫ должны сохранить ...",
      "answer": "природу"
    },
    {
      "text": "Факторы, изменение которых во времени повторяются регулярно, называют",
      "answer": "Периодическими"
    },
    {
      "text": "Существование и развитие вида к изменению внешних условий не безгранична, лежит в каких-то пределах экологического воздействия, которые определяются как пределы толерантности, это закон",
      "answer": "Шелфорда"
    },
    {
      "text": "«Закон минимума», согласно которому выносливость организма определяется самым слабым звеном в цепи его экологических потребностей. Это закон",
      "answer": "Либиха"
    },
    {
      "text": "Территория с присущим ей комплексом экологических факторов среды, занимаемая сообществом, называется",
      "answer": "Биотоп"
    },
    {
      "text": "Для городских экосистем не характерно",
      "answer": "Видовое разнообразие"
    },
    {
      "text": "Способность организма выдерживать изменения условий жизни, называется",
      "answer": "Толерантность"
    },
    {
      "text": "Организмы, хорошо адаптирующиеся к широкому изменению состояния среды называются",
      "answer": "Толерантными видами"
    }
  ]
}